guestbook/__init__.py
guestbook/static/main.css
guestbook/templates/index.html
Rambo_zhou_guestbook2-1.0.0.dist-info/METADATA
Rambo_zhou_guestbook2-1.0.0.dist-info/WHEEL
Rambo_zhou_guestbook2-1.0.0.dist-info/entry_points.txt
Rambo_zhou_guestbook2-1.0.0.dist-info/top_level.txt
Rambo_zhou_guestbook2-1.0.0.dist-info/RECORD
