Metadata-Version: 2.1
Name: Rambo-zhou-guestbook2
Version: 1.0.0
Summary: A guestbook web application.
Home-page: UNKNOWN
Author: UNKNOWN
Author-email: UNKNOWN
License: BSD License
Keywords: web,guestbook
Platform: UNKNOWN
Classifier: Development Status :: 4 - Beta
Classifier: Framework :: Flask
Classifier: License :: OSI Approved :: BSD License
Classifier: Programming Language :: Python
Classifier: Programming Language :: Python :: 3.6
Requires-Dist: Flask
